<Entity xmlns:meta="Editor">
	<Components>
		<Position />
		<AI>
			<Speed>1</Speed>
			<AI>BasicMonster</AI>
		</AI>
		<Statistics>
			<Statistics meta:RefKey="Statistics">
				<MaxHP>90</MaxHP>
				<Power>8</Power>
				<Regeneration>0.01</Regeneration>
			</Statistics>
			<EquipmentWeight>Light</EquipmentWeight>
			<Death meta:RefKey="ParticleEffect">
				<Name>Death</Name>
			</Death>
			<Attack>
				<Damage>1</Damage>
				<Range>5</Range>
				<FlightEffect meta:RefKey="ParticleEffect">
					<Name>Arrow</Name>
					<Colour>153,153,153,255</Colour>
					<Scale>0.5</Scale>
				</FlightEffect>
			</Attack>
		</Statistics>
		<DirectionalSprite>
			<Animations>
				<Animation>
					<Name>idle</Name>
					<Up meta:RefKey="Sprite">
						<Name>Oryx/uf_split/uf_heroes/priest</Name>
						<DrawActualSize>true</DrawActualSize>
					</Up>
					<Down meta:RefKey="Sprite">
						<Name>Oryx/uf_split/uf_heroes/priest</Name>
						<DrawActualSize>true</DrawActualSize>
					</Down>
				</Animation>
			</Animations>
		</DirectionalSprite>
		<Ability>
			<Abilities>
				<AbilityData>
					<Name>Heal</Name>
					<Icon meta:RefKey="Sprite">
						<Name>Oryx/uf_split/uf_items/book_green</Name>
						<DrawActualSize>true</DrawActualSize>
					</Icon>
					<Ability meta:RefKey="ActionSequence">
						<Timeline>
							<SelectAllies>
								<Count>5</Count>
							</SelectAllies>
							<Heal>
								<Time>0.0239726044</Time>
							</Heal>
							<BlockTurn>
								<Time>0.219178081</Time>
							</BlockTurn>
							<SelectAllies>
								<Time>0.2431507</Time>
								<Count>5</Count>
							</SelectAllies>
							<Heal>
								<Time>0.267808229</Time>
							</Heal>
							<BlockTurn>
								<Time>0.4719178</Time>
							</BlockTurn>
							<SelectAllies>
								<Time>0.495205462</Time>
								<Count>5</Count>
							</SelectAllies>
							<Heal>
								<Time>0.5171233</Time>
							</Heal>
							<BlockTurn>
								<Time>0.714056849</Time>
							</BlockTurn>
						</Timeline>
						<Timeline>
							<DestinationRenderable>
								<Duration LockDuration="False">0.200684935</Duration>
								<Renderable meta:RefKey="ParticleEffect">
									<Name>Heal</Name>
									<Colour>0,235,71,255</Colour>
								</Renderable>
								<RenderablePerTile>true</RenderablePerTile>
							</DestinationRenderable>
							<DestinationRenderable>
								<Time>0.2431507</Time>
								<Duration LockDuration="False">0.213698611</Duration>
								<Renderable meta:RefKey="ParticleEffect">
									<Name>Heal</Name>
									<Colour>0,235,71,255</Colour>
								</Renderable>
								<RenderablePerTile>true</RenderablePerTile>
							</DestinationRenderable>
							<DestinationRenderable>
								<Time>0.495205462</Time>
								<Duration LockDuration="False">0.206849337</Duration>
								<Renderable meta:RefKey="ParticleEffect">
									<Name>Heal</Name>
									<Colour>0,235,71,255</Colour>
								</Renderable>
								<RenderablePerTile>true</RenderablePerTile>
							</DestinationRenderable>
						</Timeline>
					</Ability>
					<Cooldown>9,15</Cooldown>
					<Range>9</Range>
				</AbilityData>
				<AbilityData>
					<Name>Fascinate</Name>
					<Icon meta:RefKey="Sprite">
						<Name>Oryx/uf_split/uf_items/heart_red_full</Name>
						<DrawActualSize>true</DrawActualSize>
						<Colour>255,103,234,255</Colour>
					</Icon>
					<Ability meta:RefKey="ActionSequence">
						<Timeline>
							<Stun>
								<Time>0.272602737</Time>
								<Count>3+rnd(3)</Count>
							</Stun>
						</Timeline>
						<Timeline>
							<MovementRenderable>
								<Duration LockDuration="False">0.1979452</Duration>
								<Renderable meta:RefKey="ParticleEffect">
									<Name>Bolt</Name>
									<Colour>230,34,222,255</Colour>
								</Renderable>
							</MovementRenderable>
							<DestinationRenderable>
								<Time>0.1979452</Time>
								<Duration LockDuration="False">0.1979452</Duration>
								<Renderable meta:RefKey="ParticleEffect">
									<Name>HeartBurst</Name>
								</Renderable>
							</DestinationRenderable>
						</Timeline>
					</Ability>
					<Cooldown>3,11</Cooldown>
					<Range>9</Range>
				</AbilityData>
				<AbilityData>
					<Name>Guardian Angel</Name>
					<Icon meta:RefKey="Sprite">
						<Name>Oryx/uf_split/uf_items/cloak_glow</Name>
						<DrawActualSize>true</DrawActualSize>
					</Icon>
					<Ability meta:RefKey="ActionSequence">
						<Timeline>
							<SelectAllies>
								<Condition>hp/maxhp</Condition>
							</SelectAllies>
							<Heal>
								<Time>0.0222426467</Time>
								<Amount>0.1</Amount>
							</Heal>
						</Timeline>
					</Ability>
					<Cooldown>3,6</Cooldown>
					<Range>9</Range>
				</AbilityData>
			</Abilities>
		</Ability>
		<Name>
			<Name>Nemora</Name>
			<Title>The Blessed Healer</Title>
		</Name>
	</Components>
</Entity>